amdapy/__init__.py
amdapy/amda.py
amdapy/csv.py
amdapy/ddtime.py
amdapy/editor.py
amdapy/http_index.py
amdapy/pds.py
amdapy/pdsdump.py
amdapy/session.py
amdapy/setup.py
amdapy/spase.py
amdapy/str_utils.py
amdapy/vidata.py
amdapy/viview.py
amdapy/amdaWSClient/__init__.py
amdapy/amdaWSClient/client.py
amdapy/amdaWSClient/obstree.py
amdapy/amdaWSClient/version.py
amdapy/core/__init__.py
amdapy/core/dataset.py
amdapy/core/parameter.py
amdapy/core/provider.py
amdapy/core/timespan.py
amdapy/core/variable.py
amdapy/provider/__init__.py
amdapy/scripts/__init__.py
amdapy/scripts/ace_swepam_stea.py
amdapy/scripts/add_phi_theta.py
amdapy/scripts/check_sampling.py
amdapy/scripts/data_check.py
amdapy/scripts/helios1_idist.py
amdapy/scripts/helios_dists.py
amdapy/scripts/iter_amda_datasets.py
amdapy-0.1.1.dist-info/LICENSE
amdapy-0.1.1.dist-info/METADATA
amdapy-0.1.1.dist-info/WHEEL
amdapy-0.1.1.dist-info/top_level.txt
amdapy-0.1.1.dist-info/RECORD
